MANIFEST.in
README.md
README.rst
requirements.txt
setup.cfg
setup.py
lucy/__init__.py
lucy/lucy.py
lucy.egg-info/PKG-INFO
lucy.egg-info/SOURCES.txt
lucy.egg-info/dependency_links.txt
lucy.egg-info/entry_points.txt
lucy.egg-info/pbr.json
lucy.egg-info/requires.txt
lucy.egg-info/top_level.txt