Metadata-Version: 1.0
Name: lucy
Version: 1.1
Summary: Lucy generates a LICENSE file for your project from the command line for you.
Home-page: https://github.com/pattu777/Lucy
Author: Chinmaya Kr. Patanaik
Author-email: patanaikchinmaya@gmail.com
License: MIT
Keywords: license,github,command line,cli
Platform: UNKNOWN
